MANIFEST.in
README.rst
setup.py
django_forumbr.egg-info/PKG-INFO
django_forumbr.egg-info/SOURCES.txt
django_forumbr.egg-info/dependency_links.txt
django_forumbr.egg-info/requires.txt
django_forumbr.egg-info/top_level.txt
forum/__init__.py
forum/admin.py
forum/app_settings.py
forum/constants.py
forum/exceptions.py
forum/forms.py
forum/markup.py
forum/models.py
forum/tests.py
forum/urls.py
forum/validators.py
forum/views.py
forum/static/css/forum/foundation.min.css
forum/static/css/forum/more.css
forum/static/css/forum/normalize.css
forum/static/css/forum/styles.css
forum/static/img/forum/avatar/dull.png
forum/static/img/forum/avatar/dull_face.png
forum/static/js/forum/foundation.min.js
forum/static/js/forum/markitup/jquery.markitup.js
forum/static/js/forum/markitup/sets/bbcode/readme.txt
forum/static/js/forum/markitup/sets/bbcode/set.js
forum/static/js/forum/markitup/sets/bbcode/style.css
forum/static/js/forum/markitup/sets/bbcode/images/bold.png
forum/static/js/forum/markitup/sets/bbcode/images/clean.png
forum/static/js/forum/markitup/sets/bbcode/images/code.png
forum/static/js/forum/markitup/sets/bbcode/images/fonts.png
forum/static/js/forum/markitup/sets/bbcode/images/italic.png
forum/static/js/forum/markitup/sets/bbcode/images/link.png
forum/static/js/forum/markitup/sets/bbcode/images/list-bullet.png
forum/static/js/forum/markitup/sets/bbcode/images/list-item.png
forum/static/js/forum/markitup/sets/bbcode/images/list-numeric.png
forum/static/js/forum/markitup/sets/bbcode/images/picture.png
forum/static/js/forum/markitup/sets/bbcode/images/preview.png
forum/static/js/forum/markitup/sets/bbcode/images/quotes.png
forum/static/js/forum/markitup/sets/bbcode/images/stroke.png
forum/static/js/forum/markitup/sets/bbcode/images/underline.png
forum/static/js/forum/markitup/sets/default/set.js
forum/static/js/forum/markitup/sets/default/style.css
forum/static/js/forum/markitup/sets/default/images/bold.png
forum/static/js/forum/markitup/sets/default/images/clean.png
forum/static/js/forum/markitup/sets/default/images/image.png
forum/static/js/forum/markitup/sets/default/images/italic.png
forum/static/js/forum/markitup/sets/default/images/link.png
