Metadata-Version: 1.0
Name: django-forumbr
Version: 0.4.0.1
Summary: Simple and complete django forum solution
Home-page: https://bitbucket.org/italomaia/django-forumbr
Author: Italo Maia
Author-email: italo.maia@gmail.com
License: http://www.apache.org/licenses/LICENSE-2.0
Keywords: django forum python
Platform: UNKNOWN
